{
    "base_name": "platinum haewark hamlet watchstone",
    "required_state": {
        "rarity": "magic",
        "magic_mods": [
            {
                "prefix": "mature",
                "suffix": null,
                "prefix_exact": null,
                "suffix_exact": null
            },
            {
                "prefix": "overripe",
                "suffix": null,
                "prefix_exact": null,
                "suffix_exact": null
            }
        ],
        "rare_mods": []
    }
}
